{
    "instaloader": {
        "node_type": "Post",
        "version": "4.13.1"
    },
    "node": {
        "__typename": "GraphVideo",
        "accessibility_caption": null,
        "caption": "Nasi Gandul Khas Pati\nJalan H. Agus Salim No. 30 B, Kebon Sirih, Jakarta Pusat (Kawasan Sabang)\n\nMenu:\n1. Nasi Gandul Komplit Rp 26.000\n2. Tempe Goreng Rp 2.000\n3. Es Teh Tawar Rp 2.000\n4. Sate Telur Puyuh Rp 5.000\n5. Perkedel Rp 5.000\n6. Sate Paru Rp 6.000\n7. Sate Ati Ampela Rp 6.000\n\nfollow: @nex_inox\n\n#nasi #gandul #khas #pati #nasigandul #nasipati #nasigandulpati #nasikhaspati #nasigandulkhaspati #khaspati #komplit #nasigandulkomplit #jakarta #jkt #food #makansiang #makan #kuliner #kulinerjakarta #kulinerjakartapusat #jakartapusat #nex #inox #kirnos #nexinox #nexkirnos #nex_inox #nex_kirnos",
        "comments": 0,
        "date": 1717644649,
        "display_url": "https://instagram.fcgk30-1.fna.fbcdn.net/v/t51.29350-15/447471889_1106447323753193_1398101143908313813_n.jpg?stp=dst-jpg_e15&efg=eyJ2ZW5jb2RlX3RhZyI6ImltYWdlX3VybGdlbi41NDB4OTYwLnNkci5mMjkzNTAuZGVmYXVsdF9jb3Zlcl9mcmFtZSJ9&_nc_ht=instagram.fcgk30-1.fna.fbcdn.net&_nc_cat=105&_nc_ohc=8-EEnSYpWyUQ7kNvgGZPcmX&_nc_gid=1906a0762da146c482d3b535806893a9&edm=AEhyXUkBAAAA&ccb=7-5&ig_cache_key=MzM4NDE3MDc3Mjc5MTk4OTQzMg%3D%3D.3-ccb7-5&oh=00_AYDaBJ0lT2r-I0ecEh90g6VwVDZB-S2hD-Q6AcxnJKEoCQ&oe=6705142A&_nc_sid=8f1549",
        "edge_media_preview_like": {
            "count": 26
        },
        "id": "3384170772791989432",
        "iphone_struct": {
            "__typename": "XDTMediaDict",
            "accessibility_caption": null,
            "ad_id": null,
            "affiliate_info": null,
            "all_previous_submitters": null,
            "audience": null,
            "boost_unavailable_identifier": null,
            "boost_unavailable_reason": null,
            "boosted_status": null,
            "can_reshare": null,
            "can_see_insights_as_brand": false,
            "can_viewer_reshare": true,
            "caption": {
                "created_at": 1717644656,
                "has_translation": null,
                "pk": "18436409107029583",
                "text": "Nasi Gandul Khas Pati\nJalan H. Agus Salim No. 30 B, Kebon Sirih, Jakarta Pusat (Kawasan Sabang)\n\nMenu:\n1. Nasi Gandul Komplit Rp 26.000\n2. Tempe Goreng Rp 2.000\n3. Es Teh Tawar Rp 2.000\n4. Sate Telur Puyuh Rp 5.000\n5. Perkedel Rp 5.000\n6. Sate Paru Rp 6.000\n7. Sate Ati Ampela Rp 6.000\n\nfollow: @nex_inox\n\n#nasi #gandul #khas #pati #nasigandul #nasipati #nasigandulpati #nasikhaspati #nasigandulkhaspati #khaspati #komplit #nasigandulkomplit #jakarta #jkt #food #makansiang #makan #kuliner #kulinerjakarta #kulinerjakartapusat #jakartapusat #nex #inox #kirnos #nexinox #nexkirnos #nex_inox #nex_kirnos"
            },
            "caption_is_edited": false,
            "carousel_media": null,
            "carousel_media_count": null,
            "carousel_parent_id": null,
            "clips_attribution_info": null,
            "clips_metadata": {
                "achievements_info": {
                    "show_achievements": false
                },
                "audio_type": "licensed_music",
                "music_info": {
                    "music_asset_info": {
                        "audio_cluster_id": "2312381358959575",
                        "display_artist": "Sarah Suhairi, Alfie Zumi",
                        "is_explicit": false,
                        "title": "SAH (DJ Remix)"
                    },
                    "music_consumption_info": {
                        "is_trending_in_clips": false,
                        "should_mute_audio": false,
                        "should_mute_audio_reason": ""
                    }
                },
                "original_sound_info": null
            },
            "coauthor_producers": [],
            "code": "C72_WNDhpS4",
            "comment_count": 0,
            "commenting_disabled_for_viewer": null,
            "comments": null,
            "comments_disabled": null,
            "display_uri": "https://instagram.fcgk30-1.fna.fbcdn.net/v/t51.29350-15/447471889_1106447323753193_1398101143908313813_n.jpg?stp=c0.210.540.540a_dst-jpg_e15&_nc_ht=instagram.fcgk30-1.fna.fbcdn.net&_nc_cat=105&_nc_ohc=8-EEnSYpWyUQ7kNvgGZPcmX&_nc_gid=1906a0762da146c482d3b535806893a9&edm=AEhyXUkBAAAA&ccb=7-5&oh=00_AYD64I9aNO_EHSeeCWKk-AyhXiuOI5m7mMZeOJE5OMONNw&oe=6705142A&_nc_sid=8f1549",
            "expiring_at": null,
            "explore": null,
            "facepile_top_likers": null,
            "feed_demotion_control": null,
            "feed_recs_demotion_control": null,
            "follow_hashtag_info": null,
            "group": null,
            "has_audio": true,
            "has_liked": false,
            "has_viewer_saved": null,
            "headline": null,
            "id": "3384170772791989432_62546679986",
            "ig_media_sharing_disabled": false,
            "image_versions2": {
                "candidates": [
                    {
                        "height": 960,
                        "url": "https://instagram.fcgk30-1.fna.fbcdn.net/v/t51.29350-15/447471889_1106447323753193_1398101143908313813_n.jpg?stp=dst-jpg_e15&efg=eyJ2ZW5jb2RlX3RhZyI6ImltYWdlX3VybGdlbi41NDB4OTYwLnNkci5mMjkzNTAuZGVmYXVsdF9jb3Zlcl9mcmFtZSJ9&_nc_ht=instagram.fcgk30-1.fna.fbcdn.net&_nc_cat=105&_nc_ohc=8-EEnSYpWyUQ7kNvgGZPcmX&_nc_gid=1906a0762da146c482d3b535806893a9&edm=AEhyXUkBAAAA&ccb=7-5&ig_cache_key=MzM4NDE3MDc3Mjc5MTk4OTQzMg%3D%3D.3-ccb7-5&oh=00_AYDaBJ0lT2r-I0ecEh90g6VwVDZB-S2hD-Q6AcxnJKEoCQ&oe=6705142A&_nc_sid=8f1549",
                        "width": 540
                    },
                    {
                        "height": 853,
                        "url": "https://instagram.fcgk30-1.fna.fbcdn.net/v/t51.29350-15/447471889_1106447323753193_1398101143908313813_n.jpg?stp=dst-jpg_e15_p480x480&efg=eyJ2ZW5jb2RlX3RhZyI6ImltYWdlX3VybGdlbi41NDB4OTYwLnNkci5mMjkzNTAuZGVmYXVsdF9jb3Zlcl9mcmFtZSJ9&_nc_ht=instagram.fcgk30-1.fna.fbcdn.net&_nc_cat=105&_nc_ohc=8-EEnSYpWyUQ7kNvgGZPcmX&_nc_gid=1906a0762da146c482d3b535806893a9&edm=AEhyXUkBAAAA&ccb=7-5&ig_cache_key=MzM4NDE3MDc3Mjc5MTk4OTQzMg%3D%3D.3-ccb7-5&oh=00_AYBmd0a7cJ5XouHFB07KbG7D_nf3oqcsxY6fVG3h_IuIxQ&oe=6705142A&_nc_sid=8f1549",
                        "width": 480
                    },
                    {
                        "height": 569,
                        "url": "https://instagram.fcgk30-1.fna.fbcdn.net/v/t51.29350-15/447471889_1106447323753193_1398101143908313813_n.jpg?stp=dst-jpg_e15_p320x320&efg=eyJ2ZW5jb2RlX3RhZyI6ImltYWdlX3VybGdlbi41NDB4OTYwLnNkci5mMjkzNTAuZGVmYXVsdF9jb3Zlcl9mcmFtZSJ9&_nc_ht=instagram.fcgk30-1.fna.fbcdn.net&_nc_cat=105&_nc_ohc=8-EEnSYpWyUQ7kNvgGZPcmX&_nc_gid=1906a0762da146c482d3b535806893a9&edm=AEhyXUkBAAAA&ccb=7-5&ig_cache_key=MzM4NDE3MDc3Mjc5MTk4OTQzMg%3D%3D.3-ccb7-5&oh=00_AYDFzDMEAUVgM0Gua6kS09g5MEANvf3OnA7APBMRLkaPcw&oe=6705142A&_nc_sid=8f1549",
                        "width": 320
                    },
                    {
                        "height": 427,
                        "url": "https://instagram.fcgk30-1.fna.fbcdn.net/v/t51.29350-15/447471889_1106447323753193_1398101143908313813_n.jpg?stp=dst-jpg_e15_p240x240&efg=eyJ2ZW5jb2RlX3RhZyI6ImltYWdlX3VybGdlbi41NDB4OTYwLnNkci5mMjkzNTAuZGVmYXVsdF9jb3Zlcl9mcmFtZSJ9&_nc_ht=instagram.fcgk30-1.fna.fbcdn.net&_nc_cat=105&_nc_ohc=8-EEnSYpWyUQ7kNvgGZPcmX&_nc_gid=1906a0762da146c482d3b535806893a9&edm=AEhyXUkBAAAA&ccb=7-5&ig_cache_key=MzM4NDE3MDc3Mjc5MTk4OTQzMg%3D%3D.3-ccb7-5&oh=00_AYDRus_N798vDPEIwOOQORkm__WKDRlwH-_ypKa9D6zSHA&oe=6705142A&_nc_sid=8f1549",
                        "width": 240
                    },
                    {
                        "height": 1080,
                        "url": "https://instagram.fcgk30-1.fna.fbcdn.net/v/t51.29350-15/447471889_1106447323753193_1398101143908313813_n.jpg?stp=c0.210.540.540a_dst-jpg_e15&efg=eyJ2ZW5jb2RlX3RhZyI6ImltYWdlX3VybGdlbi41NDB4OTYwLnNkci5mMjkzNTAuZGVmYXVsdF9jb3Zlcl9mcmFtZSJ9&_nc_ht=instagram.fcgk30-1.fna.fbcdn.net&_nc_cat=105&_nc_ohc=8-EEnSYpWyUQ7kNvgGZPcmX&_nc_gid=1906a0762da146c482d3b535806893a9&edm=AEhyXUkBAAAA&ccb=7-5&ig_cache_key=MzM4NDE3MDc3Mjc5MTk4OTQzMg%3D%3D.3-ccb7-5&oh=00_AYD64I9aNO_EHSeeCWKk-AyhXiuOI5m7mMZeOJE5OMONNw&oe=6705142A&_nc_sid=8f1549",
                        "width": 1080
                    },
                    {
                        "height": 750,
                        "url": "https://instagram.fcgk30-1.fna.fbcdn.net/v/t51.29350-15/447471889_1106447323753193_1398101143908313813_n.jpg?stp=c0.210.540.540a_dst-jpg_e15&efg=eyJ2ZW5jb2RlX3RhZyI6ImltYWdlX3VybGdlbi41NDB4OTYwLnNkci5mMjkzNTAuZGVmYXVsdF9jb3Zlcl9mcmFtZSJ9&_nc_ht=instagram.fcgk30-1.fna.fbcdn.net&_nc_cat=105&_nc_ohc=8-EEnSYpWyUQ7kNvgGZPcmX&_nc_gid=1906a0762da146c482d3b535806893a9&edm=AEhyXUkBAAAA&ccb=7-5&ig_cache_key=MzM4NDE3MDc3Mjc5MTk4OTQzMg%3D%3D.3-ccb7-5&oh=00_AYD64I9aNO_EHSeeCWKk-AyhXiuOI5m7mMZeOJE5OMONNw&oe=6705142A&_nc_sid=8f1549",
                        "width": 750
                    },
                    {
                        "height": 640,
                        "url": "https://instagram.fcgk30-1.fna.fbcdn.net/v/t51.29350-15/447471889_1106447323753193_1398101143908313813_n.jpg?stp=c0.210.540.540a_dst-jpg_e15&efg=eyJ2ZW5jb2RlX3RhZyI6ImltYWdlX3VybGdlbi41NDB4OTYwLnNkci5mMjkzNTAuZGVmYXVsdF9jb3Zlcl9mcmFtZSJ9&_nc_ht=instagram.fcgk30-1.fna.fbcdn.net&_nc_cat=105&_nc_ohc=8-EEnSYpWyUQ7kNvgGZPcmX&_nc_gid=1906a0762da146c482d3b535806893a9&edm=AEhyXUkBAAAA&ccb=7-5&ig_cache_key=MzM4NDE3MDc3Mjc5MTk4OTQzMg%3D%3D.3-ccb7-5&oh=00_AYD64I9aNO_EHSeeCWKk-AyhXiuOI5m7mMZeOJE5OMONNw&oe=6705142A&_nc_sid=8f1549",
                        "width": 640
                    },
                    {
                        "height": 480,
                        "url": "https://instagram.fcgk30-1.fna.fbcdn.net/v/t51.29350-15/447471889_1106447323753193_1398101143908313813_n.jpg?stp=c0.210.540.540a_dst-jpg_e15_s480x480&efg=eyJ2ZW5jb2RlX3RhZyI6ImltYWdlX3VybGdlbi41NDB4OTYwLnNkci5mMjkzNTAuZGVmYXVsdF9jb3Zlcl9mcmFtZSJ9&_nc_ht=instagram.fcgk30-1.fna.fbcdn.net&_nc_cat=105&_nc_ohc=8-EEnSYpWyUQ7kNvgGZPcmX&_nc_gid=1906a0762da146c482d3b535806893a9&edm=AEhyXUkBAAAA&ccb=7-5&ig_cache_key=MzM4NDE3MDc3Mjc5MTk4OTQzMg%3D%3D.3-ccb7-5&oh=00_AYB8uX6TQQ7MKP4xRbCeD24qSZwzybfW3yPNuKLL23RcIg&oe=6705142A&_nc_sid=8f1549",
                        "width": 480
                    },
                    {
                        "height": 320,
                        "url": "https://instagram.fcgk30-1.fna.fbcdn.net/v/t51.29350-15/447471889_1106447323753193_1398101143908313813_n.jpg?stp=c0.210.540.540a_dst-jpg_e15_s320x320&efg=eyJ2ZW5jb2RlX3RhZyI6ImltYWdlX3VybGdlbi41NDB4OTYwLnNkci5mMjkzNTAuZGVmYXVsdF9jb3Zlcl9mcmFtZSJ9&_nc_ht=instagram.fcgk30-1.fna.fbcdn.net&_nc_cat=105&_nc_ohc=8-EEnSYpWyUQ7kNvgGZPcmX&_nc_gid=1906a0762da146c482d3b535806893a9&edm=AEhyXUkBAAAA&ccb=7-5&ig_cache_key=MzM4NDE3MDc3Mjc5MTk4OTQzMg%3D%3D.3-ccb7-5&oh=00_AYDrybK5Y4SOrbSihp3hAOfnguzAjhKU3omVsDGhCfw05Q&oe=6705142A&_nc_sid=8f1549",
                        "width": 320
                    },
                    {
                        "height": 240,
                        "url": "https://instagram.fcgk30-1.fna.fbcdn.net/v/t51.29350-15/447471889_1106447323753193_1398101143908313813_n.jpg?stp=c0.210.540.540a_dst-jpg_e15_s240x240&efg=eyJ2ZW5jb2RlX3RhZyI6ImltYWdlX3VybGdlbi41NDB4OTYwLnNkci5mMjkzNTAuZGVmYXVsdF9jb3Zlcl9mcmFtZSJ9&_nc_ht=instagram.fcgk30-1.fna.fbcdn.net&_nc_cat=105&_nc_ohc=8-EEnSYpWyUQ7kNvgGZPcmX&_nc_gid=1906a0762da146c482d3b535806893a9&edm=AEhyXUkBAAAA&ccb=7-5&ig_cache_key=MzM4NDE3MDc3Mjc5MTk4OTQzMg%3D%3D.3-ccb7-5&oh=00_AYAQRVamChueSX1kCr_p3yWmWD6O8fu1ckVgodf1XTTuFA&oe=6705142A&_nc_sid=8f1549",
                        "width": 240
                    },
                    {
                        "height": 150,
                        "url": "https://instagram.fcgk30-1.fna.fbcdn.net/v/t51.29350-15/447471889_1106447323753193_1398101143908313813_n.jpg?stp=c0.210.540.540a_dst-jpg_e15_s150x150&efg=eyJ2ZW5jb2RlX3RhZyI6ImltYWdlX3VybGdlbi41NDB4OTYwLnNkci5mMjkzNTAuZGVmYXVsdF9jb3Zlcl9mcmFtZSJ9&_nc_ht=instagram.fcgk30-1.fna.fbcdn.net&_nc_cat=105&_nc_ohc=8-EEnSYpWyUQ7kNvgGZPcmX&_nc_gid=1906a0762da146c482d3b535806893a9&edm=AEhyXUkBAAAA&ccb=7-5&ig_cache_key=MzM4NDE3MDc3Mjc5MTk4OTQzMg%3D%3D.3-ccb7-5&oh=00_AYCAr1VbumxDIXiqu0Sbu2lB1TwYRXHvdHyEX7d7B2u5yQ&oe=6705142A&_nc_sid=8f1549",
                        "width": 150
                    }
                ]
            },
            "inventory_source": null,
            "invited_coauthor_producers": [],
            "is_dash_eligible": null,
            "is_paid_partnership": false,
            "is_seen": null,
            "like_and_view_counts_disabled": false,
            "like_count": 26,
            "link": null,
            "location": {
                "lat": -6.185226,
                "lng": 106.82497,
                "name": "Nasi Gandul Khas Pati, Sabang",
                "pk": 134938173997250,
                "profile_pic_url": null
            },
            "main_feed_carousel_starting_media_id": null,
            "media_cropping_info": {
                "square_crop": {
                    "crop_bottom": 0.0,
                    "crop_left": 0.0,
                    "crop_right": 0.0,
                    "crop_top": 0.0
                }
            },
            "media_level_comment_controls": null,
            "media_overlay_info": null,
            "media_type": 2,
            "number_of_qualities": null,
            "open_carousel_submission_state": null,
            "organic_tracking_token": "eyJ2ZXJzaW9uIjo1LCJwYXlsb2FkIjp7ImlzX2FuYWx5dGljc190cmFja2VkIjp0cnVlLCJ1dWlkIjoiMTkwNmEwNzYyZGExNDZjNDgyZDNiNTM1ODA2ODkzYTkzMzg0MTcwNzcyNzkxOTg5NDMyIn0sInNpZ25hdHVyZSI6IiJ9",
            "original_height": 1920,
            "original_width": 1080,
            "owner": {
                "__typename": "XDTUserDict",
                "friendship_status": null,
                "id": "62546679986",
                "is_embeds_disabled": null,
                "is_private": false,
                "is_unpublished": false,
                "is_verified": false,
                "pk": "62546679986",
                "profile_pic_url": "https://instagram.fcgk30-1.fna.fbcdn.net/v/t51.2885-19/397294756_1378378562775945_6684160243028153414_n.jpg?stp=dst-jpg_s150x150&_nc_ht=instagram.fcgk30-1.fna.fbcdn.net&_nc_cat=109&_nc_ohc=O8wcn_GXz6QQ7kNvgHCjzLr&_nc_gid=1906a0762da146c482d3b535806893a9&edm=AEhyXUkBAAAA&ccb=7-5&oh=00_AYC1RjbALsOuDe21ks577SQEW15UZHn0J79OP7s2nmOq2A&oe=67052ED8&_nc_sid=8f1549",
                "show_account_transparency_details": true,
                "supervision_info": null,
                "transparency_label": null,
                "transparency_product": null,
                "transparency_product_enabled": false,
                "username": "nex_inox"
            },
            "photo_of_you": false,
            "pk": "3384170772791989432",
            "preview": null,
            "previous_submitter": null,
            "product_type": "clips",
            "saved_collection_ids": null,
            "share_urls": null,
            "sharing_friction_info": {
                "bloks_app_url": null,
                "should_have_sharing_friction": false
            },
            "social_context": null,
            "sponsor_tags": null,
            "story_cta": null,
            "taken_at": 1717644649,
            "thumbnails": null,
            "timeline_pinned_user_ids": [],
            "title": null,
            "top_likers": null,
            "upcoming_event": null,
            "user": {
                "__typename": "XDTUserDict",
                "friendship_status": null,
                "full_name": "Nex Kirnos | Food Influencer",
                "hd_profile_pic_url_info": {
                    "url": "https://instagram.fcgk30-1.fna.fbcdn.net/v/t51.2885-19/397294756_1378378562775945_6684160243028153414_n.jpg?_nc_ht=instagram.fcgk30-1.fna.fbcdn.net&_nc_cat=109&_nc_ohc=O8wcn_GXz6QQ7kNvgHCjzLr&_nc_gid=1906a0762da146c482d3b535806893a9&edm=AEhyXUkBAAAA&ccb=7-5&oh=00_AYCnldMQrZHVNEctyMrBlyFrbHXnvEDbcy7gh-HkHzPj5A&oe=67052ED8&_nc_sid=8f1549"
                },
                "id": "62546679986",
                "is_embeds_disabled": null,
                "is_private": false,
                "is_unpublished": false,
                "is_verified": false,
                "latest_besties_reel_media": null,
                "latest_reel_media": null,
                "live_broadcast_id": null,
                "live_broadcast_visibility": null,
                "pk": "62546679986",
                "profile_pic_url": "https://instagram.fcgk30-1.fna.fbcdn.net/v/t51.2885-19/397294756_1378378562775945_6684160243028153414_n.jpg?stp=dst-jpg_s150x150&_nc_ht=instagram.fcgk30-1.fna.fbcdn.net&_nc_cat=109&_nc_ohc=O8wcn_GXz6QQ7kNvgHCjzLr&_nc_gid=1906a0762da146c482d3b535806893a9&edm=AEhyXUkBAAAA&ccb=7-5&oh=00_AYC1RjbALsOuDe21ks577SQEW15UZHn0J79OP7s2nmOq2A&oe=67052ED8&_nc_sid=8f1549",
                "seen": null,
                "supervision_info": null,
                "username": "nex_inox"
            },
            "usertags": null,
            "video_dash_manifest": null,
            "video_versions": [
                {
                    "height": 853,
                    "type": 101,
                    "url": "https://instagram.fcgk29-1.fna.fbcdn.net/o1/v/t16/f1/m82/714A9BD8B00F7FB037D1CFC774FA84A6_video_dashinit.mp4?stp=dst-mp4&efg=eyJxZV9ncm91cHMiOiJbXCJpZ193ZWJfZGVsaXZlcnlfdnRzX290ZlwiXSIsInZlbmNvZGVfdGFnIjoidnRzX3ZvZF91cmxnZW4uY2xpcHMuYzIuNzIwLmJhc2VsaW5lIn0&_nc_cat=104&vs=417858861080220_194853152&_nc_vs=HBksFQIYT2lnX3hwdl9yZWVsc19wZXJtYW5lbnRfcHJvZC83MTRBOUJEOEIwMEY3RkIwMzdEMUNGQzc3NEZBODRBNl92aWRlb19kYXNoaW5pdC5tcDQVAALIAQAVAhg6cGFzc3Rocm91Z2hfZXZlcnN0b3JlL0dLRGtweHJhWnVDQm1CY0RBQktycWZFTkxyNWNicV9FQUFBRhUCAsgBACgAGAAbABUAACaG8Mf3yf6HQBUCKAJDMywXQDAqfvnbItEYEmRhc2hfYmFzZWxpbmVfMV92MREAdf4HAA%3D%3D&ccb=9-4&oh=00_AYCyKeDP5reBanhjfpuhBI1XxYIv6DB5r3sgfWPE-oqhUA&oe=6701220E&_nc_sid=8f1549",
                    "width": 480
                },
                {
                    "height": 853,
                    "type": 103,
                    "url": "https://instagram.fcgk29-1.fna.fbcdn.net/o1/v/t16/f1/m82/714A9BD8B00F7FB037D1CFC774FA84A6_video_dashinit.mp4?stp=dst-mp4&efg=eyJxZV9ncm91cHMiOiJbXCJpZ193ZWJfZGVsaXZlcnlfdnRzX290ZlwiXSIsInZlbmNvZGVfdGFnIjoidnRzX3ZvZF91cmxnZW4uY2xpcHMuYzIuNzIwLmJhc2VsaW5lIn0&_nc_cat=104&vs=417858861080220_194853152&_nc_vs=HBksFQIYT2lnX3hwdl9yZWVsc19wZXJtYW5lbnRfcHJvZC83MTRBOUJEOEIwMEY3RkIwMzdEMUNGQzc3NEZBODRBNl92aWRlb19kYXNoaW5pdC5tcDQVAALIAQAVAhg6cGFzc3Rocm91Z2hfZXZlcnN0b3JlL0dLRGtweHJhWnVDQm1CY0RBQktycWZFTkxyNWNicV9FQUFBRhUCAsgBACgAGAAbABUAACaG8Mf3yf6HQBUCKAJDMywXQDAqfvnbItEYEmRhc2hfYmFzZWxpbmVfMV92MREAdf4HAA%3D%3D&ccb=9-4&oh=00_AYCyKeDP5reBanhjfpuhBI1XxYIv6DB5r3sgfWPE-oqhUA&oe=6701220E&_nc_sid=8f1549",
                    "width": 480
                },
                {
                    "height": 853,
                    "type": 102,
                    "url": "https://instagram.fcgk29-1.fna.fbcdn.net/o1/v/t16/f1/m82/714A9BD8B00F7FB037D1CFC774FA84A6_video_dashinit.mp4?stp=dst-mp4&efg=eyJxZV9ncm91cHMiOiJbXCJpZ193ZWJfZGVsaXZlcnlfdnRzX290ZlwiXSIsInZlbmNvZGVfdGFnIjoidnRzX3ZvZF91cmxnZW4uY2xpcHMuYzIuNzIwLmJhc2VsaW5lIn0&_nc_cat=104&vs=417858861080220_194853152&_nc_vs=HBksFQIYT2lnX3hwdl9yZWVsc19wZXJtYW5lbnRfcHJvZC83MTRBOUJEOEIwMEY3RkIwMzdEMUNGQzc3NEZBODRBNl92aWRlb19kYXNoaW5pdC5tcDQVAALIAQAVAhg6cGFzc3Rocm91Z2hfZXZlcnN0b3JlL0dLRGtweHJhWnVDQm1CY0RBQktycWZFTkxyNWNicV9FQUFBRhUCAsgBACgAGAAbABUAACaG8Mf3yf6HQBUCKAJDMywXQDAqfvnbItEYEmRhc2hfYmFzZWxpbmVfMV92MREAdf4HAA%3D%3D&ccb=9-4&oh=00_AYCyKeDP5reBanhjfpuhBI1XxYIv6DB5r3sgfWPE-oqhUA&oe=6701220E&_nc_sid=8f1549",
                    "width": 480
                }
            ],
            "view_count": null
        },
        "is_video": true,
        "owner": {
            "full_name": "Nex Kirnos | Food Influencer",
            "id": "62546679986",
            "iphone_struct": {
                "__typename": "XDTUserDict",
                "friendship_status": null,
                "full_name": "Nex Kirnos | Food Influencer",
                "hd_profile_pic_url_info": {
                    "url": "https://instagram.fcgk30-1.fna.fbcdn.net/v/t51.2885-19/397294756_1378378562775945_6684160243028153414_n.jpg?_nc_ht=instagram.fcgk30-1.fna.fbcdn.net&_nc_cat=109&_nc_ohc=O8wcn_GXz6QQ7kNvgHCjzLr&_nc_gid=1906a0762da146c482d3b535806893a9&edm=AEhyXUkBAAAA&ccb=7-5&oh=00_AYCnldMQrZHVNEctyMrBlyFrbHXnvEDbcy7gh-HkHzPj5A&oe=67052ED8&_nc_sid=8f1549"
                },
                "id": "62546679986",
                "is_embeds_disabled": null,
                "is_private": false,
                "is_unpublished": false,
                "is_verified": false,
                "latest_besties_reel_media": null,
                "latest_reel_media": null,
                "live_broadcast_id": null,
                "live_broadcast_visibility": null,
                "pk": "62546679986",
                "profile_pic_url": "https://instagram.fcgk30-1.fna.fbcdn.net/v/t51.2885-19/397294756_1378378562775945_6684160243028153414_n.jpg?stp=dst-jpg_s150x150&_nc_ht=instagram.fcgk30-1.fna.fbcdn.net&_nc_cat=109&_nc_ohc=O8wcn_GXz6QQ7kNvgHCjzLr&_nc_gid=1906a0762da146c482d3b535806893a9&edm=AEhyXUkBAAAA&ccb=7-5&oh=00_AYC1RjbALsOuDe21ks577SQEW15UZHn0J79OP7s2nmOq2A&oe=67052ED8&_nc_sid=8f1549",
                "seen": null,
                "supervision_info": null,
                "username": "nex_inox"
            },
            "is_private": false,
            "profile_pic_url_hd": "https://instagram.fcgk30-1.fna.fbcdn.net/v/t51.2885-19/397294756_1378378562775945_6684160243028153414_n.jpg?stp=dst-jpg_s150x150&_nc_ht=instagram.fcgk30-1.fna.fbcdn.net&_nc_cat=109&_nc_ohc=O8wcn_GXz6QQ7kNvgHCjzLr&_nc_gid=1906a0762da146c482d3b535806893a9&edm=AEhyXUkBAAAA&ccb=7-5&oh=00_AYC1RjbALsOuDe21ks577SQEW15UZHn0J79OP7s2nmOq2A&oe=67052ED8&_nc_sid=8f1549",
            "username": "nex_inox"
        },
        "shortcode": "C72_WNDhpS4",
        "title": null,
        "video_url": "https://instagram.fcgk29-1.fna.fbcdn.net/o1/v/t16/f1/m82/714A9BD8B00F7FB037D1CFC774FA84A6_video_dashinit.mp4?stp=dst-mp4&efg=eyJxZV9ncm91cHMiOiJbXCJpZ193ZWJfZGVsaXZlcnlfdnRzX290ZlwiXSIsInZlbmNvZGVfdGFnIjoidnRzX3ZvZF91cmxnZW4uY2xpcHMuYzIuNzIwLmJhc2VsaW5lIn0&_nc_cat=104&vs=417858861080220_194853152&_nc_vs=HBksFQIYT2lnX3hwdl9yZWVsc19wZXJtYW5lbnRfcHJvZC83MTRBOUJEOEIwMEY3RkIwMzdEMUNGQzc3NEZBODRBNl92aWRlb19kYXNoaW5pdC5tcDQVAALIAQAVAhg6cGFzc3Rocm91Z2hfZXZlcnN0b3JlL0dLRGtweHJhWnVDQm1CY0RBQktycWZFTkxyNWNicV9FQUFBRhUCAsgBACgAGAAbABUAACaG8Mf3yf6HQBUCKAJDMywXQDAqfvnbItEYEmRhc2hfYmFzZWxpbmVfMV92MREAdf4HAA%3D%3D&ccb=9-4&oh=00_AYCyKeDP5reBanhjfpuhBI1XxYIv6DB5r3sgfWPE-oqhUA&oe=6701220E&_nc_sid=8f1549",
        "viewer_has_liked": false
    }
}