{
    "instaloader": {
        "node_type": "Post",
        "version": "4.14.1"
    },
    "node": {
        "__typename": "GraphVideo",
        "accessibility_caption": null,
        "caption": "Tongseng Paling Enak di Jakarta Pusat\n\nPaling Enak Versi Nex Kirnos\nEps. 1\nTongseng Paling Enak\n\n1. Warung Sate Tongseng Sri Rejeki\nJl. Pejambon I Gg. II No.24 4, RT.4/RW.1, Gambir, Jakarta Pusat\n\n2. Warung Sate Solo Pak Kumis\nJL. Kesehatan III No. 3, Gambir, Jakarta Pusat\n\n3. Tongseng Anti Kolesterol Pak Kadir\nJL. Musi No. 44, Gambir, Jakarta Pusat\n\nfollow: @nex_inox @sate_solo_p.kumis\n\n#tongseng #palingenak #enak #tongsengenak #tongsengpalingenak #terenak #tongsengterenak  #jkt #food #makansiang #makan #kuliner #kulinerjakarta #kulinerjakpus #jakarta #nex #inox #kirnos #nexinox #nexkirnos #nex_inox #nex_kirnos",
        "comments": 8,
        "date": 1748145046,
        "display_url": "https://scontent-sin2-1.cdninstagram.com/v/t51.71878-15/500678303_3129438310538518_1553435866560546281_n.jpg?stp=dst-jpg_e15_tt6&_nc_cat=100&ig_cache_key=MzY0MDAyNTExNDkyNzk2NDMyNA%3D%3D.3-ccb1-7&ccb=1-7&_nc_sid=58cdad&efg=eyJ2ZW5jb2RlX3RhZyI6InhwaWRzLjY0MHgxMTM2LnNkciJ9&_nc_ohc=ZobkAam8yuoQ7kNvwFqdyA7&_nc_oc=AdmfclR2Wjnh8Z45QLlFzK5LpfcIA4YukxU56zuNRnMS-uN8lJu_e5NpJauFTeQClDU&_nc_ad=z-m&_nc_cid=0&_nc_zt=23&_nc_ht=scontent-sin2-1.cdninstagram.com&_nc_gid=myyifW7p0bgdXD-Io5Lbdw&oh=00_AfN2DgUHtkVAk07SoOUSclaD_V7-KR50vsz36WLLarFcqw&oe=6851D1F2",
        "edge_media_preview_like": {
            "count": 29
        },
        "id": "3640025114927964324",
        "iphone_struct": {
            "__typename": "XDTMediaDict",
            "accessibility_caption": null,
            "ad_id": null,
            "affiliate_info": null,
            "all_previous_submitters": null,
            "audience": null,
            "boost_unavailable_identifier": null,
            "boost_unavailable_reason": null,
            "boosted_status": null,
            "can_reshare": null,
            "can_see_insights_as_brand": false,
            "can_viewer_reshare": true,
            "caption": {
                "created_at": 1748145047,
                "has_translation": true,
                "pk": "18062227559279342",
                "text": "Tongseng Paling Enak di Jakarta Pusat\n\nPaling Enak Versi Nex Kirnos\nEps. 1\nTongseng Paling Enak\n\n1. Warung Sate Tongseng Sri Rejeki\nJl. Pejambon I Gg. II No.24 4, RT.4/RW.1, Gambir, Jakarta Pusat\n\n2. Warung Sate Solo Pak Kumis\nJL. Kesehatan III No. 3, Gambir, Jakarta Pusat\n\n3. Tongseng Anti Kolesterol Pak Kadir\nJL. Musi No. 44, Gambir, Jakarta Pusat\n\nfollow: @nex_inox @sate_solo_p.kumis\n\n#tongseng #palingenak #enak #tongsengenak #tongsengpalingenak #terenak #tongsengterenak  #jkt #food #makansiang #makan #kuliner #kulinerjakarta #kulinerjakpus #jakarta #nex #inox #kirnos #nexinox #nexkirnos #nex_inox #nex_kirnos"
            },
            "caption_is_edited": false,
            "carousel_media": null,
            "carousel_media_count": null,
            "carousel_parent_id": null,
            "clips_attribution_info": null,
            "clips_metadata": {
                "achievements_info": {
                    "show_achievements": false
                },
                "audio_type": "original_sounds",
                "music_info": null,
                "original_sound_info": {
                    "audio_asset_id": "964719215575639",
                    "consumption_info": {
                        "is_trending_in_clips": false,
                        "should_mute_audio_reason": "",
                        "should_mute_audio_reason_type": null
                    },
                    "ig_artist": {
                        "id": "62546679986",
                        "username": "nex_inox"
                    },
                    "is_explicit": false,
                    "original_audio_title": "Original audio",
                    "should_mute_audio": false
                }
            },
            "coauthor_producers": [],
            "code": "DKD945syCCk",
            "comment_count": 8,
            "commenting_disabled_for_viewer": null,
            "comments": null,
            "comments_disabled": null,
            "display_uri": null,
            "expiring_at": null,
            "explore": null,
            "facepile_top_likers": [],
            "feed_demotion_control": null,
            "feed_recs_demotion_control": null,
            "follow_hashtag_info": null,
            "group": null,
            "has_audio": true,
            "has_liked": false,
            "has_viewer_saved": null,
            "headline": null,
            "id": "3640025114927964324_62546679986",
            "ig_media_sharing_disabled": false,
            "image_versions2": {
                "candidates": [
                    {
                        "height": 1136,
                        "url": "https://scontent-sin2-1.cdninstagram.com/v/t51.71878-15/500678303_3129438310538518_1553435866560546281_n.jpg?stp=dst-jpg_e15_tt6&_nc_cat=100&ig_cache_key=MzY0MDAyNTExNDkyNzk2NDMyNA%3D%3D.3-ccb1-7&ccb=1-7&_nc_sid=58cdad&efg=eyJ2ZW5jb2RlX3RhZyI6InhwaWRzLjY0MHgxMTM2LnNkciJ9&_nc_ohc=ZobkAam8yuoQ7kNvwFqdyA7&_nc_oc=AdmfclR2Wjnh8Z45QLlFzK5LpfcIA4YukxU56zuNRnMS-uN8lJu_e5NpJauFTeQClDU&_nc_ad=z-m&_nc_cid=0&_nc_zt=23&_nc_ht=scontent-sin2-1.cdninstagram.com&_nc_gid=myyifW7p0bgdXD-Io5Lbdw&oh=00_AfN2DgUHtkVAk07SoOUSclaD_V7-KR50vsz36WLLarFcqw&oe=6851D1F2",
                        "width": 640
                    },
                    {
                        "height": 852,
                        "url": "https://scontent-sin2-1.cdninstagram.com/v/t51.71878-15/500678303_3129438310538518_1553435866560546281_n.jpg?stp=dst-jpg_e15_p480x480_tt6&_nc_cat=100&ig_cache_key=MzY0MDAyNTExNDkyNzk2NDMyNA%3D%3D.3-ccb1-7&ccb=1-7&_nc_sid=58cdad&efg=eyJ2ZW5jb2RlX3RhZyI6InhwaWRzLjY0MHgxMTM2LnNkciJ9&_nc_ohc=ZobkAam8yuoQ7kNvwFqdyA7&_nc_oc=AdmfclR2Wjnh8Z45QLlFzK5LpfcIA4YukxU56zuNRnMS-uN8lJu_e5NpJauFTeQClDU&_nc_ad=z-m&_nc_cid=0&_nc_zt=23&_nc_ht=scontent-sin2-1.cdninstagram.com&_nc_gid=myyifW7p0bgdXD-Io5Lbdw&oh=00_AfNn26ePHmwTcC4gA33EJWJAbAjDOgU3epJxEU9n83G8Fg&oe=6851D1F2",
                        "width": 480
                    },
                    {
                        "height": 568,
                        "url": "https://scontent-sin2-1.cdninstagram.com/v/t51.71878-15/500678303_3129438310538518_1553435866560546281_n.jpg?stp=dst-jpg_e15_p320x320_tt6&_nc_cat=100&ig_cache_key=MzY0MDAyNTExNDkyNzk2NDMyNA%3D%3D.3-ccb1-7&ccb=1-7&_nc_sid=58cdad&efg=eyJ2ZW5jb2RlX3RhZyI6InhwaWRzLjY0MHgxMTM2LnNkciJ9&_nc_ohc=ZobkAam8yuoQ7kNvwFqdyA7&_nc_oc=AdmfclR2Wjnh8Z45QLlFzK5LpfcIA4YukxU56zuNRnMS-uN8lJu_e5NpJauFTeQClDU&_nc_ad=z-m&_nc_cid=0&_nc_zt=23&_nc_ht=scontent-sin2-1.cdninstagram.com&_nc_gid=myyifW7p0bgdXD-Io5Lbdw&oh=00_AfPAvKRcfKDCcPP-EXwEhfEjXeQiO9wK2cdVpNtWriBKfw&oe=6851D1F2",
                        "width": 320
                    },
                    {
                        "height": 426,
                        "url": "https://scontent-sin2-1.cdninstagram.com/v/t51.71878-15/500678303_3129438310538518_1553435866560546281_n.jpg?stp=dst-jpg_e15_p240x240_tt6&_nc_cat=100&ig_cache_key=MzY0MDAyNTExNDkyNzk2NDMyNA%3D%3D.3-ccb1-7&ccb=1-7&_nc_sid=58cdad&efg=eyJ2ZW5jb2RlX3RhZyI6InhwaWRzLjY0MHgxMTM2LnNkciJ9&_nc_ohc=ZobkAam8yuoQ7kNvwFqdyA7&_nc_oc=AdmfclR2Wjnh8Z45QLlFzK5LpfcIA4YukxU56zuNRnMS-uN8lJu_e5NpJauFTeQClDU&_nc_ad=z-m&_nc_cid=0&_nc_zt=23&_nc_ht=scontent-sin2-1.cdninstagram.com&_nc_gid=myyifW7p0bgdXD-Io5Lbdw&oh=00_AfOYpNWL-WtX4hP3_kJ4jONm_d3GBVnam_IcrHR005XgBw&oe=6851D1F2",
                        "width": 240
                    },
                    {
                        "height": 640,
                        "url": "https://scontent-sin2-1.cdninstagram.com/v/t51.71878-15/500678303_3129438310538518_1553435866560546281_n.jpg?stp=c0.248.640.640a_dst-jpg_e15_s640x640_tt6&_nc_cat=100&ig_cache_key=MzY0MDAyNTExNDkyNzk2NDMyNA%3D%3D.3-ccb1-7&ccb=1-7&_nc_sid=58cdad&efg=eyJ2ZW5jb2RlX3RhZyI6InhwaWRzLjY0MHgxMTM2LnNkciJ9&_nc_ohc=ZobkAam8yuoQ7kNvwFqdyA7&_nc_oc=AdmfclR2Wjnh8Z45QLlFzK5LpfcIA4YukxU56zuNRnMS-uN8lJu_e5NpJauFTeQClDU&_nc_ad=z-m&_nc_cid=0&_nc_zt=23&_nc_ht=scontent-sin2-1.cdninstagram.com&_nc_gid=myyifW7p0bgdXD-Io5Lbdw&oh=00_AfOyjXN8FOn79B3btr_eNc5JpMr78l0nhMn5gt1yeplpUQ&oe=6851D1F2",
                        "width": 640
                    },
                    {
                        "height": 640,
                        "url": "https://scontent-sin2-1.cdninstagram.com/v/t51.71878-15/500678303_3129438310538518_1553435866560546281_n.jpg?stp=c0.248.640.640a_dst-jpg_e15_s640x640_tt6&_nc_cat=100&ig_cache_key=MzY0MDAyNTExNDkyNzk2NDMyNA%3D%3D.3-ccb1-7&ccb=1-7&_nc_sid=58cdad&efg=eyJ2ZW5jb2RlX3RhZyI6InhwaWRzLjY0MHgxMTM2LnNkciJ9&_nc_ohc=ZobkAam8yuoQ7kNvwFqdyA7&_nc_oc=AdmfclR2Wjnh8Z45QLlFzK5LpfcIA4YukxU56zuNRnMS-uN8lJu_e5NpJauFTeQClDU&_nc_ad=z-m&_nc_cid=0&_nc_zt=23&_nc_ht=scontent-sin2-1.cdninstagram.com&_nc_gid=myyifW7p0bgdXD-Io5Lbdw&oh=00_AfOyjXN8FOn79B3btr_eNc5JpMr78l0nhMn5gt1yeplpUQ&oe=6851D1F2",
                        "width": 640
                    },
                    {
                        "height": 640,
                        "url": "https://scontent-sin2-1.cdninstagram.com/v/t51.71878-15/500678303_3129438310538518_1553435866560546281_n.jpg?stp=c0.248.640.640a_dst-jpg_e15_s640x640_tt6&_nc_cat=100&ig_cache_key=MzY0MDAyNTExNDkyNzk2NDMyNA%3D%3D.3-ccb1-7&ccb=1-7&_nc_sid=58cdad&efg=eyJ2ZW5jb2RlX3RhZyI6InhwaWRzLjY0MHgxMTM2LnNkciJ9&_nc_ohc=ZobkAam8yuoQ7kNvwFqdyA7&_nc_oc=AdmfclR2Wjnh8Z45QLlFzK5LpfcIA4YukxU56zuNRnMS-uN8lJu_e5NpJauFTeQClDU&_nc_ad=z-m&_nc_cid=0&_nc_zt=23&_nc_ht=scontent-sin2-1.cdninstagram.com&_nc_gid=myyifW7p0bgdXD-Io5Lbdw&oh=00_AfOyjXN8FOn79B3btr_eNc5JpMr78l0nhMn5gt1yeplpUQ&oe=6851D1F2",
                        "width": 640
                    },
                    {
                        "height": 480,
                        "url": "https://scontent-sin2-1.cdninstagram.com/v/t51.71878-15/500678303_3129438310538518_1553435866560546281_n.jpg?stp=c0.248.640.640a_dst-jpg_e15_s480x480_tt6&_nc_cat=100&ig_cache_key=MzY0MDAyNTExNDkyNzk2NDMyNA%3D%3D.3-ccb1-7&ccb=1-7&_nc_sid=58cdad&efg=eyJ2ZW5jb2RlX3RhZyI6InhwaWRzLjY0MHgxMTM2LnNkciJ9&_nc_ohc=ZobkAam8yuoQ7kNvwFqdyA7&_nc_oc=AdmfclR2Wjnh8Z45QLlFzK5LpfcIA4YukxU56zuNRnMS-uN8lJu_e5NpJauFTeQClDU&_nc_ad=z-m&_nc_cid=0&_nc_zt=23&_nc_ht=scontent-sin2-1.cdninstagram.com&_nc_gid=myyifW7p0bgdXD-Io5Lbdw&oh=00_AfO7tR5Ht6ld6RfJBZHGig5JjMFQJ8D4SxzoprssiDcX-w&oe=6851D1F2",
                        "width": 480
                    },
                    {
                        "height": 320,
                        "url": "https://scontent-sin2-1.cdninstagram.com/v/t51.71878-15/500678303_3129438310538518_1553435866560546281_n.jpg?stp=c0.248.640.640a_dst-jpg_e15_s320x320_tt6&_nc_cat=100&ig_cache_key=MzY0MDAyNTExNDkyNzk2NDMyNA%3D%3D.3-ccb1-7&ccb=1-7&_nc_sid=58cdad&efg=eyJ2ZW5jb2RlX3RhZyI6InhwaWRzLjY0MHgxMTM2LnNkciJ9&_nc_ohc=ZobkAam8yuoQ7kNvwFqdyA7&_nc_oc=AdmfclR2Wjnh8Z45QLlFzK5LpfcIA4YukxU56zuNRnMS-uN8lJu_e5NpJauFTeQClDU&_nc_ad=z-m&_nc_cid=0&_nc_zt=23&_nc_ht=scontent-sin2-1.cdninstagram.com&_nc_gid=myyifW7p0bgdXD-Io5Lbdw&oh=00_AfPGyt-tz3hffvIadw0AabvbG70ezgrirgWwbEklJbic4Q&oe=6851D1F2",
                        "width": 320
                    },
                    {
                        "height": 240,
                        "url": "https://scontent-sin2-1.cdninstagram.com/v/t51.71878-15/500678303_3129438310538518_1553435866560546281_n.jpg?stp=c0.248.640.640a_dst-jpg_e15_s240x240_tt6&_nc_cat=100&ig_cache_key=MzY0MDAyNTExNDkyNzk2NDMyNA%3D%3D.3-ccb1-7&ccb=1-7&_nc_sid=58cdad&efg=eyJ2ZW5jb2RlX3RhZyI6InhwaWRzLjY0MHgxMTM2LnNkciJ9&_nc_ohc=ZobkAam8yuoQ7kNvwFqdyA7&_nc_oc=AdmfclR2Wjnh8Z45QLlFzK5LpfcIA4YukxU56zuNRnMS-uN8lJu_e5NpJauFTeQClDU&_nc_ad=z-m&_nc_cid=0&_nc_zt=23&_nc_ht=scontent-sin2-1.cdninstagram.com&_nc_gid=myyifW7p0bgdXD-Io5Lbdw&oh=00_AfPksEzsU6dLvxVljYxZJ4uUojVhtpCzO7TqeaqoE9-tpg&oe=6851D1F2",
                        "width": 240
                    },
                    {
                        "height": 150,
                        "url": "https://scontent-sin2-1.cdninstagram.com/v/t51.71878-15/500678303_3129438310538518_1553435866560546281_n.jpg?stp=c0.248.640.640a_dst-jpg_e15_s150x150_tt6&_nc_cat=100&ig_cache_key=MzY0MDAyNTExNDkyNzk2NDMyNA%3D%3D.3-ccb1-7&ccb=1-7&_nc_sid=58cdad&efg=eyJ2ZW5jb2RlX3RhZyI6InhwaWRzLjY0MHgxMTM2LnNkciJ9&_nc_ohc=ZobkAam8yuoQ7kNvwFqdyA7&_nc_oc=AdmfclR2Wjnh8Z45QLlFzK5LpfcIA4YukxU56zuNRnMS-uN8lJu_e5NpJauFTeQClDU&_nc_ad=z-m&_nc_cid=0&_nc_zt=23&_nc_ht=scontent-sin2-1.cdninstagram.com&_nc_gid=myyifW7p0bgdXD-Io5Lbdw&oh=00_AfP3npkF35vysrspMnfbVr4YvnFYBSVGcNLurjaE6_DZIQ&oe=6851D1F2",
                        "width": 150
                    }
                ]
            },
            "inventory_source": null,
            "invited_coauthor_producers": [],
            "is_dash_eligible": 1,
            "is_paid_partnership": false,
            "is_seen": null,
            "like_and_view_counts_disabled": false,
            "like_count": 29,
            "link": null,
            "location": {
                "lat": -6.176205,
                "lng": 106.833052,
                "name": "Warung Sate \"Tongseng \"Sri Rejeki",
                "pk": 116830003087173,
                "profile_pic_url": null
            },
            "main_feed_carousel_starting_media_id": null,
            "media_cropping_info": null,
            "media_level_comment_controls": null,
            "media_overlay_info": null,
            "media_type": 2,
            "number_of_qualities": 8,
            "open_carousel_submission_state": null,
            "organic_tracking_token": "eyJ2ZXJzaW9uIjo1LCJwYXlsb2FkIjp7ImlzX2FuYWx5dGljc190cmFja2VkIjp0cnVlLCJ1dWlkIjoiNGE0YzdjMGM4ZTI0NGU1YWI1OWQwYmUyMWNjNDU0OTMzNjQwMDI1MTE0OTI3OTY0MzI0Iiwic2VydmVyX3Rva2VuIjoiMTc0OTgxNjM4NjE2M3wzNjQwMDI1MTE0OTI3OTY0MzI0fDczOTY5MzgwNzI5fDA4NTdhYTdmNTliNTNlYmUzOWIzNjY1MjkxOGRmY2VlYmRkNzY0MjE0OWQ3ODVjNWFiNzEwMDA2Yzc3ODliZmMifSwic2lnbmF0dXJlIjoiIn0=",
            "original_height": 1920,
            "original_width": 1080,
            "owner": {
                "__typename": "XDTUserDict",
                "friendship_status": {
                    "following": true,
                    "is_bestie": false,
                    "is_feed_favorite": false,
                    "is_restricted": false
                },
                "id": "62546679986",
                "is_embeds_disabled": false,
                "is_private": false,
                "is_unpublished": false,
                "is_verified": false,
                "pk": "62546679986",
                "profile_pic_url": "https://scontent-sin6-2.cdninstagram.com/v/t51.2885-19/397294756_1378378562775945_6684160243028153414_n.jpg?stp=dst-jpg_s150x150_tt6&_nc_ht=scontent-sin6-2.cdninstagram.com&_nc_cat=109&_nc_oc=Q6cZ2QH7ZTt8ev7K5qcDBw1GKAFnJvj0PTeHkizay6IpN_Ah9ZQFqLpvtEiDah3gxoDyVDU&_nc_ohc=sGE0xSPmQCoQ7kNvwEMoUgW&_nc_gid=myyifW7p0bgdXD-Io5Lbdw&edm=AEhyXUkBAAAA&ccb=7-5&oh=00_AfPI2Huy-IXJEOzsljKnXmXE8L7RcMAuqRaf1MIzerkJPw&oe=6851D958&_nc_sid=8f1549",
                "show_account_transparency_details": true,
                "supervision_info": null,
                "transparency_label": null,
                "transparency_product": null,
                "transparency_product_enabled": false,
                "username": "nex_inox"
            },
            "photo_of_you": false,
            "pk": "3640025114927964324",
            "preview": null,
            "previous_submitter": null,
            "product_type": "clips",
            "saved_collection_ids": null,
            "share_urls": null,
            "sharing_friction_info": {
                "bloks_app_url": null,
                "should_have_sharing_friction": false
            },
            "social_context": null,
            "sponsor_tags": null,
            "story_cta": null,
            "taken_at": 1748145046,
            "thumbnails": null,
            "timeline_pinned_user_ids": [],
            "title": null,
            "top_likers": [],
            "upcoming_event": null,
            "user": {
                "__typename": "XDTUserDict",
                "friendship_status": {
                    "following": true,
                    "is_bestie": false,
                    "is_feed_favorite": false,
                    "is_restricted": false
                },
                "full_name": "Nex Kirnos | Food Influencer",
                "hd_profile_pic_url_info": {
                    "url": "https://scontent-sin6-2.cdninstagram.com/v/t51.2885-19/397294756_1378378562775945_6684160243028153414_n.jpg?_nc_ht=scontent-sin6-2.cdninstagram.com&_nc_cat=109&_nc_oc=Q6cZ2QH7ZTt8ev7K5qcDBw1GKAFnJvj0PTeHkizay6IpN_Ah9ZQFqLpvtEiDah3gxoDyVDU&_nc_ohc=sGE0xSPmQCoQ7kNvwEMoUgW&_nc_gid=myyifW7p0bgdXD-Io5Lbdw&edm=AEhyXUkBAAAA&ccb=7-5&oh=00_AfNYls5tZnuz2VTqDDqoKGXOGdNxXmyEyLWId4oklWnoWA&oe=6851D958&_nc_sid=8f1549"
                },
                "id": "62546679986",
                "is_embeds_disabled": false,
                "is_private": false,
                "is_unpublished": false,
                "is_verified": false,
                "latest_besties_reel_media": null,
                "latest_reel_media": 0,
                "live_broadcast_id": null,
                "live_broadcast_visibility": null,
                "pk": "62546679986",
                "profile_pic_url": "https://scontent-sin6-2.cdninstagram.com/v/t51.2885-19/397294756_1378378562775945_6684160243028153414_n.jpg?stp=dst-jpg_s150x150_tt6&_nc_ht=scontent-sin6-2.cdninstagram.com&_nc_cat=109&_nc_oc=Q6cZ2QH7ZTt8ev7K5qcDBw1GKAFnJvj0PTeHkizay6IpN_Ah9ZQFqLpvtEiDah3gxoDyVDU&_nc_ohc=sGE0xSPmQCoQ7kNvwEMoUgW&_nc_gid=myyifW7p0bgdXD-Io5Lbdw&edm=AEhyXUkBAAAA&ccb=7-5&oh=00_AfPI2Huy-IXJEOzsljKnXmXE8L7RcMAuqRaf1MIzerkJPw&oe=6851D958&_nc_sid=8f1549",
                "seen": null,
                "supervision_info": null,
                "username": "nex_inox"
            },
            "usertags": {
                "in": [
                    {
                        "position": [
                            0.0,
                            0.0
                        ],
                        "user": {
                            "full_name": "Sate Solo Pak Kumis",
                            "id": "6216903954",
                            "is_verified": false,
                            "pk": "6216903954",
                            "profile_pic_url": "https://scontent-sin11-1.cdninstagram.com/v/t51.2885-19/22427545_548441832163781_4944223354514046976_n.jpg?stp=dst-jpg_s150x150_tt6&_nc_ht=scontent-sin11-1.cdninstagram.com&_nc_cat=105&_nc_oc=Q6cZ2QH7ZTt8ev7K5qcDBw1GKAFnJvj0PTeHkizay6IpN_Ah9ZQFqLpvtEiDah3gxoDyVDU&_nc_ohc=qMmtOwf1vWsQ7kNvwGgNxlu&_nc_gid=myyifW7p0bgdXD-Io5Lbdw&edm=AEhyXUkBAAAA&ccb=7-5&oh=00_AfN-EYz2pShoBCicrAiWS4JjTyPUm7WqLOxq2Ia_R0Rtdg&oe=6851FB27&_nc_sid=8f1549",
                            "username": "sate_solo_p.kumis"
                        }
                    }
                ]
            },
            "video_dash_manifest": "<?xml version=\"1.0\" encoding=\"UTF-8\"?>\n<MPD xmlns=\"urn:mpeg:dash:schema:mpd:2011\" xmlns:xsi=\"http://www.w3.org/2001/XMLSchema-instance\" xsi:schemaLocation=\"urn:mpeg:dash:schema:mpd:2011 DASH-MPD.xsd\" profiles=\"urn:mpeg:dash:profile:isoff-on-demand:2011\" minBufferTime=\"PT2S\" type=\"static\" mediaPresentationDuration=\"PT83.94014S\" FBManifestIdentifier=\"FgAYFnIyZXZldnA5LXIxZ2VuMnZwOS1hZHMZlurXo8K55q0CiOLPhuW1sgLYytD1prPAAvagk7X21LsDrKulsd3MyAO4mJKX/ZizBPTj+v6FvPUF0veM1KqM5gauy/fOvMXsDiIYE2Rhc2hfYmFzZWxpbmVfYXVkaW8iAA==\"><Period id=\"0\" duration=\"PT83.94014S\"><AdaptationSet id=\"0\" contentType=\"video\" subsegmentAlignment=\"true\" par=\"9:16\" FBUnifiedUploadResolutionMos=\"360:90\"><Representation id=\"663666066486773vd\" bandwidth=\"313742\" codecs=\"vp09.00.31.08.00.01.01.01.00\" mimeType=\"video/mp4\" sar=\"1:1\" FBEncodingTag=\"dash_r2evevp9-r1gen2vp9-ads_q20\" FBContentLength=\"3287757\" FBPlaybackResolutionMos=\"0:100,360:46.3,480:39.1,720:32.4,1080:29.1\" FBPlaybackResolutionMosConfidenceLevel=\"high\" FBPlaybackResolutionCsvqm=\"0:100,360:83.3,480:79.6,720:72.6,1080:63.4\" FBAbrPolicyTags=\"\" width=\"720\" height=\"1280\" frameRate=\"15360/512\" FBDefaultQuality=\"1\" FBQualityClass=\"hd\" FBQualityLabel=\"240p\"><BaseURL>https://scontent-sin11-1.cdninstagram.com/o1/v/t16/f2/m69/AQOHdC5kterU8sE3chItKWUzjrtk3BSmhfW1b3MnFfoxmDZk7NdgtOe9ewaww_V1TE9nIsWJS8dXIdSySdxYyGOT.mp4?strext=1&amp;_nc_cat=105&amp;_nc_sid=9ca052&amp;_nc_ht=scontent-sin11-1.cdninstagram.com&amp;_nc_ohc=McLzC_qqX2QQ7kNvwGJCzZb&amp;efg=eyJ2ZW5jb2RlX3RhZyI6ImlnLXhwdmRzLmNsaXBzLmMyLUMzLmRhc2hfcjJldmV2cDktcjFnZW4ydnA5LWFkc19xMjAiLCJ2aWRlb19pZCI6bnVsbCwib2lsX3VybGdlbl9hcHBfaWQiOi0xLCJjbGllbnRfbmFtZSI6ImlnIiwieHB2X2Fzc2V0X2lkIjoxMDUxMjkyMzczNjI2ODg2LCJ2aV91c2VjYXNlX2lkIjoxMDA5OSwiZHVyYXRpb25fcyI6ODMsInVybGdlbl9zb3VyY2UiOiJ3d3cifQ%3D%3D&amp;ccb=17-1&amp;_nc_zt=28&amp;oh=00_AfO9AIECd8XiI8lRrMO8kDQpTK8C9KoVxbqNb27KK4W20w&amp;oe=6851D507</BaseURL><SegmentBase indexRange=\"818-1053\" timescale=\"15360\" FBMinimumPrefetchRange=\"1054-18220\" FBPartialPrefetchDuration=\"2500\" FBPartialPrefetchRange=\"1054-116208\" FBFirstSegmentRange=\"1054-175963\" FBFirstSegmentDuration=\"5000\" FBSecondSegmentRange=\"175964-337941\" FBPrefetchSegmentRange=\"1054-175963\" FBPrefetchSegmentDuration=\"5000\"><Initialization range=\"0-817\"/></SegmentBase></Representation><Representation id=\"704568838722220v\" bandwidth=\"459494\" codecs=\"vp09.00.31.08.00.01.01.01.00\" mimeType=\"video/mp4\" sar=\"1:1\" FBEncodingTag=\"dash_r2evevp9-r1gen2vp9-ads_q30\" FBContentLength=\"4815115\" FBPlaybackResolutionMos=\"0:100,360:56.6,480:48.8,720:40,1080:35\" FBPlaybackResolutionMosConfidenceLevel=\"high\" FBPlaybackResolutionCsvqm=\"0:100,360:88.6,480:85.7,720:79.8,1080:70.5\" FBAbrPolicyTags=\"\" width=\"720\" height=\"1280\" frameRate=\"15360/512\" FBQualityClass=\"hd\" FBQualityLabel=\"270p\"><BaseURL>https://scontent-sin6-2.cdninstagram.com/o1/v/t16/f2/m69/AQNbhdDjApWoskKTsBp0XpgCCmgJ15YjixmQlL6HdTRykr8EkciNtsf0xJkLJwJnUQk26eQw009QMvQO5o0o2iAD.mp4?strext=1&amp;_nc_cat=109&amp;_nc_sid=9ca052&amp;_nc_ht=scontent-sin6-2.cdninstagram.com&amp;_nc_ohc=DKLSVeCzQ5kQ7kNvwGRpTaZ&amp;efg=eyJ2ZW5jb2RlX3RhZyI6ImlnLXhwdmRzLmNsaXBzLmMyLUMzLmRhc2hfcjJldmV2cDktcjFnZW4ydnA5LWFkc19xMzAiLCJ2aWRlb19pZCI6bnVsbCwib2lsX3VybGdlbl9hcHBfaWQiOi0xLCJjbGllbnRfbmFtZSI6ImlnIiwieHB2X2Fzc2V0X2lkIjoxMDUxMjkyMzczNjI2ODg2LCJ2aV91c2VjYXNlX2lkIjoxMDA5OSwiZHVyYXRpb25fcyI6ODMsInVybGdlbl9zb3VyY2UiOiJ3d3cifQ%3D%3D&amp;ccb=17-1&amp;_nc_zt=28&amp;oh=00_AfPNxaDz1Ot2QbNjcchqQBG0vmdADUrYJEOrWnFlhpEjvA&amp;oe=6851D2AB</BaseURL><SegmentBase indexRange=\"818-1053\" timescale=\"15360\" FBMinimumPrefetchRange=\"1054-24240\" FBPartialPrefetchDuration=\"2500\" FBPartialPrefetchRange=\"1054-172046\" FBFirstSegmentRange=\"1054-267304\" FBFirstSegmentDuration=\"5000\" FBSecondSegmentRange=\"267305-508195\" FBPrefetchSegmentRange=\"1054-267304\" FBPrefetchSegmentDuration=\"5000\"><Initialization range=\"0-817\"/></SegmentBase></Representation><Representation id=\"1913362116091369v\" bandwidth=\"645932\" codecs=\"vp09.00.31.08.00.01.01.01.00\" mimeType=\"video/mp4\" sar=\"1:1\" FBEncodingTag=\"dash_r2evevp9-r1gen2vp9-ads_q40\" FBContentLength=\"6768831\" FBPlaybackResolutionMos=\"0:100,360:62.9,480:55.7,720:46.3,1080:40.6\" FBPlaybackResolutionMosConfidenceLevel=\"high\" FBPlaybackResolutionCsvqm=\"0:100,360:91.9,480:89.8,720:84.7,1080:76.1\" FBAbrPolicyTags=\"\" width=\"720\" height=\"1280\" frameRate=\"15360/512\" FBQualityClass=\"hd\" FBQualityLabel=\"360p\"><BaseURL>https://scontent-sin11-2.cdninstagram.com/o1/v/t16/f2/m69/AQOShVWD0tIHy-Xoc0Wtamlkugp-LABkH_pIWC7n9p6x8WyskgHOIxB40nVokJ8VLog7OqO6MYTQjhXrxupbWa6K.mp4?strext=1&amp;_nc_cat=108&amp;_nc_sid=9ca052&amp;_nc_ht=scontent-sin11-2.cdninstagram.com&amp;_nc_ohc=47fgnETJIB4Q7kNvwHp1jg8&amp;efg=eyJ2ZW5jb2RlX3RhZyI6ImlnLXhwdmRzLmNsaXBzLmMyLUMzLmRhc2hfcjJldmV2cDktcjFnZW4ydnA5LWFkc19xNDAiLCJ2aWRlb19pZCI6bnVsbCwib2lsX3VybGdlbl9hcHBfaWQiOi0xLCJjbGllbnRfbmFtZSI6ImlnIiwieHB2X2Fzc2V0X2lkIjoxMDUxMjkyMzczNjI2ODg2LCJ2aV91c2VjYXNlX2lkIjoxMDA5OSwiZHVyYXRpb25fcyI6ODMsInVybGdlbl9zb3VyY2UiOiJ3d3cifQ%3D%3D&amp;ccb=17-1&amp;_nc_zt=28&amp;oh=00_AfOVsQdOQnDOofI09Q0RNIKVbsLJlR7n2JDrDCDqAOUGFQ&amp;oe=6851EF3C</BaseURL><SegmentBase indexRange=\"818-1053\" timescale=\"15360\" FBMinimumPrefetchRange=\"1054-31221\" FBPartialPrefetchDuration=\"2500\" FBPartialPrefetchRange=\"1054-254316\" FBFirstSegmentRange=\"1054-378884\" FBFirstSegmentDuration=\"5000\" FBSecondSegmentRange=\"378885-720956\" FBPrefetchSegmentRange=\"1054-378884\" FBPrefetchSegmentDuration=\"5000\"><Initialization range=\"0-817\"/></SegmentBase></Representation><Representation id=\"1238479211218460v\" bandwidth=\"922914\" codecs=\"vp09.00.31.08.00.01.01.01.00\" mimeType=\"video/mp4\" sar=\"1:1\" FBEncodingTag=\"dash_r2evevp9-r1gen2vp9-ads_q50\" FBContentLength=\"9671376\" FBPlaybackResolutionMos=\"0:100,360:69.7,480:63.1,720:54.2,1080:47.1\" FBPlaybackResolutionMosConfidenceLevel=\"high\" FBPlaybackResolutionCsvqm=\"0:100,360:94.9,480:93.4,720:89.5,1080:81.8\" FBAbrPolicyTags=\"avoid_on_cellular,avoid_on_cellular_intentional\" width=\"720\" height=\"1280\" frameRate=\"15360/512\" FBQualityClass=\"hd\" FBQualityLabel=\"480p\"><BaseURL>https://scontent-sin11-1.cdninstagram.com/o1/v/t16/f2/m69/AQOawFwBULKa5-UBpTt94UthUU5Oegq1_zOYVwDIqZkRyh5eRnEEgS6iJ3h7cdE9cZD2zlGdflmyupxgNnmXosOk.mp4?strext=1&amp;_nc_cat=105&amp;_nc_sid=9ca052&amp;_nc_ht=scontent-sin11-1.cdninstagram.com&amp;_nc_ohc=hcO0udgygNkQ7kNvwFK75AQ&amp;efg=eyJ2ZW5jb2RlX3RhZyI6ImlnLXhwdmRzLmNsaXBzLmMyLUMzLmRhc2hfcjJldmV2cDktcjFnZW4ydnA5LWFkc19xNTAiLCJ2aWRlb19pZCI6bnVsbCwib2lsX3VybGdlbl9hcHBfaWQiOi0xLCJjbGllbnRfbmFtZSI6ImlnIiwieHB2X2Fzc2V0X2lkIjoxMDUxMjkyMzczNjI2ODg2LCJ2aV91c2VjYXNlX2lkIjoxMDA5OSwiZHVyYXRpb25fcyI6ODMsInVybGdlbl9zb3VyY2UiOiJ3d3cifQ%3D%3D&amp;ccb=17-1&amp;_nc_zt=28&amp;oh=00_AfNVloRyHb-xrSK6bcGoZvzWMAb-KMhxSpEVhQfqmpVK7A&amp;oe=6851E897</BaseURL><SegmentBase indexRange=\"818-1053\" timescale=\"15360\" FBMinimumPrefetchRange=\"1054-39815\" FBPartialPrefetchDuration=\"2500\" FBPartialPrefetchRange=\"1054-362271\" FBFirstSegmentRange=\"1054-549659\" FBFirstSegmentDuration=\"5000\" FBSecondSegmentRange=\"549660-1056564\" FBPrefetchSegmentRange=\"1054-549659\" FBPrefetchSegmentDuration=\"5000\"><Initialization range=\"0-817\"/></SegmentBase></Representation><Representation id=\"4179337732354775v\" bandwidth=\"1273005\" codecs=\"vp09.00.31.08.00.01.01.01.00\" mimeType=\"video/mp4\" sar=\"1:1\" FBEncodingTag=\"dash_r2evevp9-r1gen2vp9-ads_q60\" FBContentLength=\"13340037\" FBPlaybackResolutionMos=\"0:100,360:75.1,480:69.6,720:61.1,1080:53.5\" FBPlaybackResolutionMosConfidenceLevel=\"high\" FBPlaybackResolutionCsvqm=\"0:100,360:96.5,480:95.6,720:92.3,1080:85.3\" FBAbrPolicyTags=\"avoid_on_cellular,avoid_on_cellular_intentional\" width=\"720\" height=\"1280\" frameRate=\"15360/512\" FBQualityClass=\"hd\" FBQualityLabel=\"540p\"><BaseURL>https://scontent-sin11-2.cdninstagram.com/o1/v/t16/f2/m69/AQO0nh5XZyz8ZRVb26C3eR7klffdETZmEzecjepwTPjfULtXVhsTgISpQ3k0iugujeVYrLatEZp2ygS1ImI7wW7w.mp4?strext=1&amp;_nc_cat=108&amp;_nc_sid=9ca052&amp;_nc_ht=scontent-sin11-2.cdninstagram.com&amp;_nc_ohc=dcfRA4gV0UgQ7kNvwFF6ddW&amp;efg=eyJ2ZW5jb2RlX3RhZyI6ImlnLXhwdmRzLmNsaXBzLmMyLUMzLmRhc2hfcjJldmV2cDktcjFnZW4ydnA5LWFkc19xNjAiLCJ2aWRlb19pZCI6bnVsbCwib2lsX3VybGdlbl9hcHBfaWQiOi0xLCJjbGllbnRfbmFtZSI6ImlnIiwieHB2X2Fzc2V0X2lkIjoxMDUxMjkyMzczNjI2ODg2LCJ2aV91c2VjYXNlX2lkIjoxMDA5OSwiZHVyYXRpb25fcyI6ODMsInVybGdlbl9zb3VyY2UiOiJ3d3cifQ%3D%3D&amp;ccb=17-1&amp;_nc_zt=28&amp;oh=00_AfPGev_7muNIYVjQ7FnsbbJf1WuuFsMoVHXLAH07FZIRIQ&amp;oe=6851F914</BaseURL><SegmentBase indexRange=\"818-1053\" timescale=\"15360\" FBMinimumPrefetchRange=\"1054-49747\" FBPartialPrefetchDuration=\"2500\" FBPartialPrefetchRange=\"1054-498702\" FBFirstSegmentRange=\"1054-776305\" FBFirstSegmentDuration=\"5000\" FBSecondSegmentRange=\"776306-1480120\" FBPrefetchSegmentRange=\"1054-776305\" FBPrefetchSegmentDuration=\"5000\"><Initialization range=\"0-817\"/></SegmentBase></Representation><Representation id=\"975626304645179v\" bandwidth=\"1738187\" codecs=\"vp09.00.31.08.00.01.01.01.00\" mimeType=\"video/mp4\" sar=\"1:1\" FBEncodingTag=\"dash_r2evevp9-r1gen2vp9-ads_q70\" FBContentLength=\"18214757\" FBPlaybackResolutionMos=\"0:100,360:79,480:74.1,720:66.4,1080:58.1\" FBPlaybackResolutionMosConfidenceLevel=\"high\" FBPlaybackResolutionCsvqm=\"0:100,360:97.9,480:97.3,720:95.1,1080:89.2\" FBAbrPolicyTags=\"avoid_on_cellular,avoid_on_cellular_intentional\" width=\"720\" height=\"1280\" frameRate=\"15360/512\" FBQualityClass=\"hd\" FBQualityLabel=\"640p\"><BaseURL>https://scontent-sin2-2.cdninstagram.com/o1/v/t16/f2/m69/AQPu8jmIR8SeBWWC-pc39c3KV3vIp_I4-lSblNvtmBJ43mO_Yq-V7lYp45pU60KWdPOjvo2qzgOks40BS1hjAlxn.mp4?strext=1&amp;_nc_cat=103&amp;_nc_sid=9ca052&amp;_nc_ht=scontent-sin2-2.cdninstagram.com&amp;_nc_ohc=Pi_BbM8KEacQ7kNvwGmDPdp&amp;efg=eyJ2ZW5jb2RlX3RhZyI6ImlnLXhwdmRzLmNsaXBzLmMyLUMzLmRhc2hfcjJldmV2cDktcjFnZW4ydnA5LWFkc19xNzAiLCJ2aWRlb19pZCI6bnVsbCwib2lsX3VybGdlbl9hcHBfaWQiOi0xLCJjbGllbnRfbmFtZSI6ImlnIiwieHB2X2Fzc2V0X2lkIjoxMDUxMjkyMzczNjI2ODg2LCJ2aV91c2VjYXNlX2lkIjoxMDA5OSwiZHVyYXRpb25fcyI6ODMsInVybGdlbl9zb3VyY2UiOiJ3d3cifQ%3D%3D&amp;ccb=17-1&amp;_nc_zt=28&amp;oh=00_AfPEUHhHbO0F6Ft7Bi_ZcRXRb3p11KgbqW9TyJSxex6ffA&amp;oe=6851F495</BaseURL><SegmentBase indexRange=\"818-1053\" timescale=\"15360\" FBMinimumPrefetchRange=\"1054-61162\" FBPartialPrefetchDuration=\"2500\" FBPartialPrefetchRange=\"1054-682548\" FBFirstSegmentRange=\"1054-1069383\" FBFirstSegmentDuration=\"5000\" FBSecondSegmentRange=\"1069384-2055181\" FBPrefetchSegmentRange=\"1054-1069383\" FBPrefetchSegmentDuration=\"5000\"><Initialization range=\"0-817\"/></SegmentBase></Representation><Representation id=\"1004072808524502v\" bandwidth=\"2366010\" codecs=\"vp09.00.31.08.00.01.01.01.00\" mimeType=\"video/mp4\" sar=\"1:1\" FBEncodingTag=\"dash_r2evevp9-r1gen2vp9-ads_q80\" FBContentLength=\"24793820\" FBPlaybackResolutionMos=\"0:100,360:82.7,480:77.5,720:71,1080:62.6\" FBPlaybackResolutionMosConfidenceLevel=\"high\" FBPlaybackResolutionCsvqm=\"0:100,360:98.83,480:98.54,720:97.2,1080:92.1\" FBAbrPolicyTags=\"avoid_on_cellular,avoid_on_cellular_intentional\" width=\"720\" height=\"1280\" frameRate=\"15360/512\" FBQualityClass=\"hd\" FBQualityLabel=\"720p\"><BaseURL>https://scontent-sin2-1.cdninstagram.com/o1/v/t16/f2/m69/AQM2YXHI6rpT8o9QcNlzEIqPjEwagtnS2qYh7rGpkIYDAJJ6DAWZYaTwyGdk4S6bxpyKgZj7dHBjdrbDeCPquhKL.mp4?strext=1&amp;_nc_cat=102&amp;_nc_sid=9ca052&amp;_nc_ht=scontent-sin2-1.cdninstagram.com&amp;_nc_ohc=pkC6TeG4tEUQ7kNvwGXmeWL&amp;efg=eyJ2ZW5jb2RlX3RhZyI6ImlnLXhwdmRzLmNsaXBzLmMyLUMzLmRhc2hfcjJldmV2cDktcjFnZW4ydnA5LWFkc19xODAiLCJ2aWRlb19pZCI6bnVsbCwib2lsX3VybGdlbl9hcHBfaWQiOi0xLCJjbGllbnRfbmFtZSI6ImlnIiwieHB2X2Fzc2V0X2lkIjoxMDUxMjkyMzczNjI2ODg2LCJ2aV91c2VjYXNlX2lkIjoxMDA5OSwiZHVyYXRpb25fcyI6ODMsInVybGdlbl9zb3VyY2UiOiJ3d3cifQ%3D%3D&amp;ccb=17-1&amp;_nc_zt=28&amp;oh=00_AfOjzsYVoD-9ZdoPyB4FdPO07-Rjg22bDtKDWVsWBKVtig&amp;oe=6851E882</BaseURL><SegmentBase indexRange=\"818-1053\" timescale=\"15360\" FBMinimumPrefetchRange=\"1054-73137\" FBPartialPrefetchDuration=\"2500\" FBPartialPrefetchRange=\"1054-905349\" FBFirstSegmentRange=\"1054-1471028\" FBFirstSegmentDuration=\"5000\" FBSecondSegmentRange=\"1471029-2841757\" FBPrefetchSegmentRange=\"1054-1471028\" FBPrefetchSegmentDuration=\"5000\"><Initialization range=\"0-817\"/></SegmentBase></Representation><Representation id=\"673825212201092v\" bandwidth=\"3794322\" codecs=\"vp09.00.40.08.00.01.01.01.00\" mimeType=\"video/mp4\" sar=\"1:1\" FBEncodingTag=\"dash_r2evevp9-r1gen2vp9-ads_q90\" FBContentLength=\"39761340\" FBPlaybackResolutionMos=\"0:100,360:87,480:83,720:77,1080:73.3\" FBPlaybackResolutionMosConfidenceLevel=\"high\" FBPlaybackResolutionCsvqm=\"0:100,360:99.422,480:99.37,720:99.035,1080:97.7\" FBAbrPolicyTags=\"avoid_on_cellular,avoid_on_cellular_intentional\" width=\"1080\" height=\"1920\" frameRate=\"15360/512\" FBQualityClass=\"hd\" FBQualityLabel=\"1080p\"><BaseURL>https://scontent-sin6-1.cdninstagram.com/o1/v/t16/f2/m69/AQMwX0H0kfYvIV63h3vdP06I7LJRnEPJ5bWHTRr4Ie7HXb1F12MTcmzwuU1_oxboki9-Ck7-XMBGzEcwmXojTgul.mp4?strext=1&amp;_nc_cat=111&amp;_nc_sid=9ca052&amp;_nc_ht=scontent-sin6-1.cdninstagram.com&amp;_nc_ohc=JZ93sAHAXGcQ7kNvwGBe-Kr&amp;efg=eyJ2ZW5jb2RlX3RhZyI6ImlnLXhwdmRzLmNsaXBzLmMyLUMzLmRhc2hfcjJldmV2cDktcjFnZW4ydnA5LWFkc19xOTAiLCJ2aWRlb19pZCI6bnVsbCwib2lsX3VybGdlbl9hcHBfaWQiOi0xLCJjbGllbnRfbmFtZSI6ImlnIiwieHB2X2Fzc2V0X2lkIjoxMDUxMjkyMzczNjI2ODg2LCJ2aV91c2VjYXNlX2lkIjoxMDA5OSwiZHVyYXRpb25fcyI6ODMsInVybGdlbl9zb3VyY2UiOiJ3d3cifQ%3D%3D&amp;ccb=17-1&amp;_nc_zt=28&amp;oh=00_AfOOBLDNgts7k0ZC7Y79aGwm5douaMTCyiZ-Rj2P8FnkCQ&amp;oe=6851EA5D</BaseURL><SegmentBase indexRange=\"818-1053\" timescale=\"15360\" FBMinimumPrefetchRange=\"1054-109633\" FBPartialPrefetchDuration=\"2500\" FBPartialPrefetchRange=\"1054-1429316\" FBFirstSegmentRange=\"1054-2371024\" FBFirstSegmentDuration=\"5000\" FBSecondSegmentRange=\"2371025-4642389\" FBPrefetchSegmentRange=\"1054-2371024\" FBPrefetchSegmentDuration=\"5000\"><Initialization range=\"0-817\"/></SegmentBase></Representation></AdaptationSet><AdaptationSet id=\"1\" contentType=\"audio\" subsegmentStartsWithSAP=\"1\" subsegmentAlignment=\"true\"><Representation id=\"1665692200818938ad\" bandwidth=\"65850\" codecs=\"mp4a.40.5\" mimeType=\"audio/mp4\" audioSamplingRate=\"44100\" FBEncodingTag=\"dash_baseline_audio_v1\" FBContentLength=\"601423\" FBAbrPolicyTags=\"\" FBDefaultQuality=\"1\"><AudioChannelConfiguration schemeIdUri=\"urn:mpeg:dash:23003:3:audio_channel_configuration:2011\" value=\"2\"/><BaseURL>https://scontent-sin6-2.cdninstagram.com/o1/v/t16/f2/m69/AQNxTcF8oE-D1--8eK_Nsu9uToyExUvB2KTSLONlzlrKHSoF95hiCvZRhIDsRIXI0Gi7nGAh_mpNZg4Itt09xIhQ.mp4?strext=1&amp;_nc_cat=109&amp;_nc_sid=9ca052&amp;_nc_ht=scontent-sin6-2.cdninstagram.com&amp;_nc_ohc=Ye1MEzf2IlkQ7kNvwGOkszK&amp;efg=eyJ2ZW5jb2RlX3RhZyI6ImlnLXhwdmRzLmNsaXBzLmMyLUMzLmRhc2hfYmFzZWxpbmVfYXVkaW9fdjEiLCJ2aWRlb19pZCI6bnVsbCwib2lsX3VybGdlbl9hcHBfaWQiOi0xLCJjbGllbnRfbmFtZSI6ImlnIiwieHB2X2Fzc2V0X2lkIjoxMDUxMjkyMzczNjI2ODg2LCJ2aV91c2VjYXNlX2lkIjoxMDA5OSwiZHVyYXRpb25fcyI6ODMsInVybGdlbl9zb3VyY2UiOiJ3d3cifQ%3D%3D&amp;ccb=17-1&amp;_nc_zt=28&amp;oh=00_AfOIP23q5hNs5S_xWTx9nk_oLY3vjxkxlTSrvqKFuwk9Ug&amp;oe=6851EE27</BaseURL><SegmentBase indexRange=\"824-1359\" timescale=\"44100\" FBMinimumPrefetchRange=\"1360-1703\" FBPartialPrefetchDuration=\"2500\" FBPartialPrefetchRange=\"1360-20291\" FBFirstSegmentRange=\"1360-16552\" FBFirstSegmentDuration=\"2021\" FBSecondSegmentRange=\"16553-32361\" FBPrefetchSegmentRange=\"1360-32361\" FBPrefetchSegmentDuration=\"4017\"><Initialization range=\"0-823\"/></SegmentBase></Representation></AdaptationSet></Period></MPD>\n",
            "video_versions": [
                {
                    "height": 1280,
                    "type": 101,
                    "url": "https://scontent-sin11-2.cdninstagram.com/o1/v/t2/f2/m86/AQMAlrCsymbm4is0BIqwgDenGFGtW3idbU-8_RjYbEl8tPyMx7ZXVrbeM5iEm9zM_txSfL3vmWpOsl-FVplm4DV19jqH45AkUeP6EME.mp4?_nc_cat=108&_nc_sid=5e9851&_nc_ht=scontent-sin11-2.cdninstagram.com&_nc_ohc=QdH4qXVimKoQ7kNvwGPDHLL&efg=eyJ2ZW5jb2RlX3RhZyI6Inhwdl9wcm9ncmVzc2l2ZS5JTlNUQUdSQU0uQ0xJUFMuQzMuNzIwLmRhc2hfYmFzZWxpbmVfMV92MSIsInhwdl9hc3NldF9pZCI6MTA1MTI5MjM3MzYyNjg4NiwidmlfdXNlY2FzZV9pZCI6MTAwOTksImR1cmF0aW9uX3MiOjgzLCJ1cmxnZW5fc291cmNlIjoid3d3In0%3D&ccb=17-1&vs=f8a6642771d06594&_nc_vs=HBksFQIYUmlnX3hwdl9yZWVsc19wZXJtYW5lbnRfc3JfcHJvZC8wRDQyRDQ5NEZFODBDRDQ3MjY1REI5MEJBMzAxQzNCNl92aWRlb19kYXNoaW5pdC5tcDQVAALIARIAFQIYOnBhc3N0aHJvdWdoX2V2ZXJzdG9yZS9HR285MHgzME9BMHFtNEVDQUhLQXBtNENQS2tFYnFfRUFBQUYVAgLIARIAKAAYABsCiAd1c2Vfb2lsATEScHJvZ3Jlc3NpdmVfcmVjaXBlATEVAAAmjMDhx6KJ3gMVAigCQzMsF0BU9U_fO2RaGBJkYXNoX2Jhc2VsaW5lXzFfdjERAHX-B2XmnQEA&_nc_zt=28&oh=00_AfPfsjn8KV4w5_caZM_bt4SGhn8hLn2WjfUR3wZHa9OyGA&oe=684DE551",
                    "width": 720
                },
                {
                    "height": 1280,
                    "type": 102,
                    "url": "https://scontent-sin11-2.cdninstagram.com/o1/v/t2/f2/m86/AQMAlrCsymbm4is0BIqwgDenGFGtW3idbU-8_RjYbEl8tPyMx7ZXVrbeM5iEm9zM_txSfL3vmWpOsl-FVplm4DV19jqH45AkUeP6EME.mp4?_nc_cat=108&_nc_sid=5e9851&_nc_ht=scontent-sin11-2.cdninstagram.com&_nc_ohc=QdH4qXVimKoQ7kNvwGPDHLL&efg=eyJ2ZW5jb2RlX3RhZyI6Inhwdl9wcm9ncmVzc2l2ZS5JTlNUQUdSQU0uQ0xJUFMuQzMuNzIwLmRhc2hfYmFzZWxpbmVfMV92MSIsInhwdl9hc3NldF9pZCI6MTA1MTI5MjM3MzYyNjg4NiwidmlfdXNlY2FzZV9pZCI6MTAwOTksImR1cmF0aW9uX3MiOjgzLCJ1cmxnZW5fc291cmNlIjoid3d3In0%3D&ccb=17-1&vs=f8a6642771d06594&_nc_vs=HBksFQIYUmlnX3hwdl9yZWVsc19wZXJtYW5lbnRfc3JfcHJvZC8wRDQyRDQ5NEZFODBDRDQ3MjY1REI5MEJBMzAxQzNCNl92aWRlb19kYXNoaW5pdC5tcDQVAALIARIAFQIYOnBhc3N0aHJvdWdoX2V2ZXJzdG9yZS9HR285MHgzME9BMHFtNEVDQUhLQXBtNENQS2tFYnFfRUFBQUYVAgLIARIAKAAYABsCiAd1c2Vfb2lsATEScHJvZ3Jlc3NpdmVfcmVjaXBlATEVAAAmjMDhx6KJ3gMVAigCQzMsF0BU9U_fO2RaGBJkYXNoX2Jhc2VsaW5lXzFfdjERAHX-B2XmnQEA&_nc_zt=28&oh=00_AfPfsjn8KV4w5_caZM_bt4SGhn8hLn2WjfUR3wZHa9OyGA&oe=684DE551",
                    "width": 720
                },
                {
                    "height": 1280,
                    "type": 103,
                    "url": "https://scontent-sin11-2.cdninstagram.com/o1/v/t2/f2/m86/AQMAlrCsymbm4is0BIqwgDenGFGtW3idbU-8_RjYbEl8tPyMx7ZXVrbeM5iEm9zM_txSfL3vmWpOsl-FVplm4DV19jqH45AkUeP6EME.mp4?_nc_cat=108&_nc_sid=5e9851&_nc_ht=scontent-sin11-2.cdninstagram.com&_nc_ohc=QdH4qXVimKoQ7kNvwGPDHLL&efg=eyJ2ZW5jb2RlX3RhZyI6Inhwdl9wcm9ncmVzc2l2ZS5JTlNUQUdSQU0uQ0xJUFMuQzMuNzIwLmRhc2hfYmFzZWxpbmVfMV92MSIsInhwdl9hc3NldF9pZCI6MTA1MTI5MjM3MzYyNjg4NiwidmlfdXNlY2FzZV9pZCI6MTAwOTksImR1cmF0aW9uX3MiOjgzLCJ1cmxnZW5fc291cmNlIjoid3d3In0%3D&ccb=17-1&vs=f8a6642771d06594&_nc_vs=HBksFQIYUmlnX3hwdl9yZWVsc19wZXJtYW5lbnRfc3JfcHJvZC8wRDQyRDQ5NEZFODBDRDQ3MjY1REI5MEJBMzAxQzNCNl92aWRlb19kYXNoaW5pdC5tcDQVAALIARIAFQIYOnBhc3N0aHJvdWdoX2V2ZXJzdG9yZS9HR285MHgzME9BMHFtNEVDQUhLQXBtNENQS2tFYnFfRUFBQUYVAgLIARIAKAAYABsCiAd1c2Vfb2lsATEScHJvZ3Jlc3NpdmVfcmVjaXBlATEVAAAmjMDhx6KJ3gMVAigCQzMsF0BU9U_fO2RaGBJkYXNoX2Jhc2VsaW5lXzFfdjERAHX-B2XmnQEA&_nc_zt=28&oh=00_AfPfsjn8KV4w5_caZM_bt4SGhn8hLn2WjfUR3wZHa9OyGA&oe=684DE551",
                    "width": 720
                }
            ],
            "view_count": null
        },
        "is_video": true,
        "owner": {
            "full_name": "Nex Kirnos | Food Influencer",
            "id": "62546679986",
            "iphone_struct": {
                "__typename": "XDTUserDict",
                "friendship_status": {
                    "following": true,
                    "is_bestie": false,
                    "is_feed_favorite": false,
                    "is_restricted": false
                },
                "full_name": "Nex Kirnos | Food Influencer",
                "hd_profile_pic_url_info": {
                    "url": "https://scontent-sin6-2.cdninstagram.com/v/t51.2885-19/397294756_1378378562775945_6684160243028153414_n.jpg?_nc_ht=scontent-sin6-2.cdninstagram.com&_nc_cat=109&_nc_oc=Q6cZ2QH7ZTt8ev7K5qcDBw1GKAFnJvj0PTeHkizay6IpN_Ah9ZQFqLpvtEiDah3gxoDyVDU&_nc_ohc=sGE0xSPmQCoQ7kNvwEMoUgW&_nc_gid=myyifW7p0bgdXD-Io5Lbdw&edm=AEhyXUkBAAAA&ccb=7-5&oh=00_AfNYls5tZnuz2VTqDDqoKGXOGdNxXmyEyLWId4oklWnoWA&oe=6851D958&_nc_sid=8f1549"
                },
                "id": "62546679986",
                "is_embeds_disabled": false,
                "is_private": false,
                "is_unpublished": false,
                "is_verified": false,
                "latest_besties_reel_media": null,
                "latest_reel_media": 0,
                "live_broadcast_id": null,
                "live_broadcast_visibility": null,
                "pk": "62546679986",
                "profile_pic_url": "https://scontent-sin6-2.cdninstagram.com/v/t51.2885-19/397294756_1378378562775945_6684160243028153414_n.jpg?stp=dst-jpg_s150x150_tt6&_nc_ht=scontent-sin6-2.cdninstagram.com&_nc_cat=109&_nc_oc=Q6cZ2QH7ZTt8ev7K5qcDBw1GKAFnJvj0PTeHkizay6IpN_Ah9ZQFqLpvtEiDah3gxoDyVDU&_nc_ohc=sGE0xSPmQCoQ7kNvwEMoUgW&_nc_gid=myyifW7p0bgdXD-Io5Lbdw&edm=AEhyXUkBAAAA&ccb=7-5&oh=00_AfPI2Huy-IXJEOzsljKnXmXE8L7RcMAuqRaf1MIzerkJPw&oe=6851D958&_nc_sid=8f1549",
                "seen": null,
                "supervision_info": null,
                "username": "nex_inox"
            },
            "is_private": false,
            "profile_pic_url_hd": "https://scontent-sin6-2.cdninstagram.com/v/t51.2885-19/397294756_1378378562775945_6684160243028153414_n.jpg?stp=dst-jpg_s150x150_tt6&_nc_ht=scontent-sin6-2.cdninstagram.com&_nc_cat=109&_nc_oc=Q6cZ2QH7ZTt8ev7K5qcDBw1GKAFnJvj0PTeHkizay6IpN_Ah9ZQFqLpvtEiDah3gxoDyVDU&_nc_ohc=sGE0xSPmQCoQ7kNvwEMoUgW&_nc_gid=myyifW7p0bgdXD-Io5Lbdw&edm=AEhyXUkBAAAA&ccb=7-5&oh=00_AfPI2Huy-IXJEOzsljKnXmXE8L7RcMAuqRaf1MIzerkJPw&oe=6851D958&_nc_sid=8f1549",
            "username": "nex_inox"
        },
        "shortcode": "DKD945syCCk",
        "title": null,
        "video_url": "https://scontent-sin11-2.cdninstagram.com/o1/v/t2/f2/m86/AQMAlrCsymbm4is0BIqwgDenGFGtW3idbU-8_RjYbEl8tPyMx7ZXVrbeM5iEm9zM_txSfL3vmWpOsl-FVplm4DV19jqH45AkUeP6EME.mp4?_nc_cat=108&_nc_sid=5e9851&_nc_ht=scontent-sin11-2.cdninstagram.com&_nc_ohc=QdH4qXVimKoQ7kNvwGPDHLL&efg=eyJ2ZW5jb2RlX3RhZyI6Inhwdl9wcm9ncmVzc2l2ZS5JTlNUQUdSQU0uQ0xJUFMuQzMuNzIwLmRhc2hfYmFzZWxpbmVfMV92MSIsInhwdl9hc3NldF9pZCI6MTA1MTI5MjM3MzYyNjg4NiwidmlfdXNlY2FzZV9pZCI6MTAwOTksImR1cmF0aW9uX3MiOjgzLCJ1cmxnZW5fc291cmNlIjoid3d3In0%3D&ccb=17-1&vs=f8a6642771d06594&_nc_vs=HBksFQIYUmlnX3hwdl9yZWVsc19wZXJtYW5lbnRfc3JfcHJvZC8wRDQyRDQ5NEZFODBDRDQ3MjY1REI5MEJBMzAxQzNCNl92aWRlb19kYXNoaW5pdC5tcDQVAALIARIAFQIYOnBhc3N0aHJvdWdoX2V2ZXJzdG9yZS9HR285MHgzME9BMHFtNEVDQUhLQXBtNENQS2tFYnFfRUFBQUYVAgLIARIAKAAYABsCiAd1c2Vfb2lsATEScHJvZ3Jlc3NpdmVfcmVjaXBlATEVAAAmjMDhx6KJ3gMVAigCQzMsF0BU9U_fO2RaGBJkYXNoX2Jhc2VsaW5lXzFfdjERAHX-B2XmnQEA&_nc_zt=28&oh=00_AfPfsjn8KV4w5_caZM_bt4SGhn8hLn2WjfUR3wZHa9OyGA&oe=684DE551",
        "viewer_has_liked": false
    }
}